apykuma/__init__.py
apykuma/py.typed
apykuma-1.2.0.dist-info/LICENSE
apykuma-1.2.0.dist-info/METADATA
apykuma-1.2.0.dist-info/WHEEL
apykuma-1.2.0.dist-info/RECORD
