Metadata-Version: 2.1
Name: apykuma
Version: 1.2.0
Summary: Small library to notify Uptime Kuma that the service is up
Home-page: https://github.com/PerchunPak/apykuma
License: MIT
Author: Perchun Pak
Author-email: pypi@perchun.it
Requires-Python: >=3.8.1,<4
Classifier: Development Status :: 5 - Production/Stable
Classifier: Intended Audience :: Developers
Classifier: License :: OSI Approved :: MIT License
Classifier: Operating System :: OS Independent
Classifier: Programming Language :: Python
Classifier: Programming Language :: Python :: 3
Classifier: Programming Language :: Python :: 3.9
Classifier: Programming Language :: Python :: 3.10
Classifier: Programming Language :: Python :: 3.11
Classifier: Programming Language :: Python :: 3.12
Classifier: Programming Language :: Python :: 3.8
Classifier: Topic :: Games/Entertainment
Classifier: Topic :: Software Development :: Libraries :: Python Modules
Classifier: Topic :: System :: Monitoring
Classifier: Typing :: Typed
Requires-Dist: aiohttp (>=3,<4)
Project-URL: Repository, https://github.com/PerchunPak/apykuma
